simconnect/SimConnect.dll
simconnect/__init__.py
simconnect/_typerpatch.py
simconnect/changedict.py
simconnect/cli.py
simconnect/datadef.py
simconnect/receiver.py
simconnect/sc.py
simconnect/scdefs.py
simconnect/scvars.json
simconnect/scvars.py
simconnect/scvars_idx.json
simconnect/winstubs.py
pysimconnect-0.2.6.dist-info/LICENSE
pysimconnect-0.2.6.dist-info/METADATA
pysimconnect-0.2.6.dist-info/WHEEL
pysimconnect-0.2.6.dist-info/entry_points.txt
pysimconnect-0.2.6.dist-info/top_level.txt
pysimconnect-0.2.6.dist-info/RECORD
