Metadata-Version: 2.1
Name: pysimconnect
Version: 0.2.6
Summary: Python wrapper for Microsoft FlightSimulator 2020 SimConnect SDK
Home-page: https://github.com/patricksurry/pysimconnect
Author: Patrick Surry
Author-email: patrick.surry@gmail.com
Project-URL: Bug Tracker, https://github.com/patricksurry/pysimconnect/issues
Keywords: pysimconnect,SimConnect,SimVars,ctypes,SDK,API,FS2020,Microsoft Flight Simulator
Classifier: Programming Language :: Python :: 3
Classifier: License :: OSI Approved :: MIT License
Classifier: Operating System :: OS Independent
Requires-Python: >=3.6
License-File: LICENSE
Requires-Dist: typer (>=0.9)
Requires-Dist: click (>=8.1)
Requires-Dist: lunr
